{"chunk_definitions":[{"chunk_id":"csetup_chunk","chunk_label":"setup","document_id":"91EA4602","expansion_state":0,"options":{"engine":"r","include":false,"label":"setup"},"row":17,"row_count":1,"visible":true},{"chunk_id":"c5a3l8oopll57","chunk_label":"unnamed-chunk-1","document_id":"91EA4602","expansion_state":0,"options":{},"row":24,"row_count":1,"visible":true},{"chunk_id":"cvcimnxr2uink","chunk_label":"unnamed-chunk-2","document_id":"91EA4602","expansion_state":0,"options":{},"row":28,"row_count":1,"visible":true},{"chunk_id":"c10mdh0o62bm4","chunk_label":"unnamed-chunk-3","document_id":"91EA4602","expansion_state":0,"options":{},"row":34,"row_count":1,"visible":true},{"chunk_id":"cd1ifa74chwvj","chunk_label":"unnamed-chunk-4","document_id":"91EA4602","expansion_state":0,"options":{},"row":46,"row_count":1,"visible":true},{"chunk_id":"civdap5atwddv","chunk_label":"unnamed-chunk-5","document_id":"91EA4602","expansion_state":0,"options":{},"row":53,"row_count":1,"visible":true},{"chunk_id":"cmgzj5sa1ofvg","chunk_label":"unnamed-chunk-6","document_id":"91EA4602","expansion_state":0,"options":{},"row":61,"row_count":1,"visible":true},{"chunk_id":"c2hji1k86qlcu","chunk_label":"unnamed-chunk-7","document_id":"91EA4602","expansion_state":0,"options":{},"row":66,"row_count":1,"visible":true},{"chunk_id":"cr9mir69egjvd","chunk_label":"unnamed-chunk-8","document_id":"91EA4602","expansion_state":0,"options":{},"row":71,"row_count":1,"visible":true},{"chunk_id":"c4hztkdxoms1v","chunk_label":"unnamed-chunk-9","document_id":"91EA4602","expansion_state":0,"options":{},"row":75,"row_count":1,"visible":true},{"chunk_id":"ch7rn7pd37yud","chunk_label":"unnamed-chunk-10","document_id":"91EA4602","expansion_state":0,"options":{},"row":80,"row_count":1,"visible":true},{"chunk_id":"cu3cx5kae7sgv","chunk_label":"unnamed-chunk-11","document_id":"91EA4602","expansion_state":0,"options":{},"row":86,"row_count":1,"visible":true},{"chunk_id":"c3kr43p4vmxb9","chunk_label":"unnamed-chunk-12","document_id":"91EA4602","expansion_state":0,"options":{},"row":90,"row_count":1,"visible":true},{"chunk_id":"cdwvwhujmtver","chunk_label":"unnamed-chunk-13","document_id":"91EA4602","expansion_state":0,"options":{},"row":95,"row_count":1,"visible":true},{"chunk_id":"cqzb3839lw2xd","chunk_label":"unnamed-chunk-14","document_id":"91EA4602","expansion_state":0,"options":{},"row":102,"row_count":1,"visible":true},{"chunk_id":"c5ti7yiqve04t","chunk_label":"unnamed-chunk-15","document_id":"91EA4602","expansion_state":0,"options":{},"row":106,"row_count":1,"visible":true},{"chunk_id":"chzj0ptujeomy","chunk_label":"unnamed-chunk-16","document_id":"91EA4602","expansion_state":0,"options":{},"row":111,"row_count":1,"visible":true},{"chunk_id":"cqbb9u54z9m5u","chunk_label":"unnamed-chunk-17","document_id":"91EA4602","expansion_state":0,"options":{},"row":115,"row_count":1,"visible":true},{"chunk_id":"c5xek3e6e99v1","chunk_label":"unnamed-chunk-18","document_id":"91EA4602","expansion_state":0,"options":{},"row":121,"row_count":1,"visible":true},{"chunk_id":"cighjg22pl5dj","chunk_label":"unnamed-chunk-19","document_id":"91EA4602","expansion_state":0,"options":{},"row":138,"row_count":1,"visible":true},{"chunk_id":"cbpwn9c4cq6ho","chunk_label":"unnamed-chunk-20","document_id":"91EA4602","expansion_state":0,"options":{},"row":143,"row_count":1,"visible":true},{"chunk_id":"crm1cgolib0et","chunk_label":"unnamed-chunk-21","document_id":"91EA4602","expansion_state":0,"options":{},"row":147,"row_count":1,"visible":true},{"chunk_id":"c5bg2tpzqj08u","chunk_label":"unnamed-chunk-22","document_id":"91EA4602","expansion_state":0,"options":{},"row":151,"row_count":1,"visible":true},{"chunk_id":"cug95heeubraf","chunk_label":"unnamed-chunk-23","document_id":"91EA4602","expansion_state":0,"options":{},"row":155,"row_count":1,"visible":true},{"chunk_id":"c2ca4dy7z2o1m","chunk_label":"unnamed-chunk-24","document_id":"91EA4602","expansion_state":0,"options":{},"row":167,"row_count":1,"visible":true},{"chunk_id":"cyzsxqohm4b9j","chunk_label":"unnamed-chunk-25","document_id":"91EA4602","expansion_state":0,"options":{},"row":175,"row_count":1,"visible":true},{"chunk_id":"ccpmu1nvbu98c","chunk_label":"unnamed-chunk-26","document_id":"91EA4602","expansion_state":0,"options":{},"row":180,"row_count":1,"visible":true},{"chunk_id":"cw55w8enqjwuv","chunk_label":"unnamed-chunk-27","document_id":"91EA4602","expansion_state":0,"options":{},"row":184,"row_count":1,"visible":true},{"chunk_id":"cma2fb5lp1uk2","chunk_label":"unnamed-chunk-28","document_id":"91EA4602","expansion_state":0,"options":{},"row":190,"row_count":1,"visible":true},{"chunk_id":"cb22zveuft1t3","chunk_label":"unnamed-chunk-29","document_id":"91EA4602","expansion_state":0,"options":{},"row":196,"row_count":1,"visible":true},{"chunk_id":"ck1m065yr0ror","chunk_label":"unnamed-chunk-30","document_id":"91EA4602","expansion_state":0,"options":{},"row":200,"row_count":1,"visible":true},{"chunk_id":"c4vowu4unrri6","chunk_label":"unnamed-chunk-31","document_id":"91EA4602","expansion_state":0,"options":{},"row":206,"row_count":1,"visible":true},{"chunk_id":"cnxi0x43qz46b","chunk_label":"unnamed-chunk-32","document_id":"91EA4602","expansion_state":0,"options":{},"row":211,"row_count":1,"visible":true},{"chunk_id":"c55h8y5kay77v","chunk_label":"unnamed-chunk-33","document_id":"91EA4602","expansion_state":0,"options":{},"row":216,"row_count":1,"visible":true},{"chunk_id":"c60mu31qix0l0","chunk_label":"unnamed-chunk-34","document_id":"91EA4602","expansion_state":0,"options":{},"row":222,"row_count":1,"visible":true},{"chunk_id":"cth1w5gncrljp","chunk_label":"unnamed-chunk-35","document_id":"91EA4602","expansion_state":0,"options":{},"row":227,"row_count":1,"visible":true},{"chunk_id":"cf9g3oz1q5aq4","chunk_label":"unnamed-chunk-36","document_id":"91EA4602","expansion_state":0,"options":{},"row":232,"row_count":1,"visible":true},{"chunk_id":"cax0yj1bz8iqt","chunk_label":"unnamed-chunk-37","document_id":"91EA4602","expansion_state":0,"options":{},"row":236,"row_count":1,"visible":true},{"chunk_id":"c54h84bfk2oti","chunk_label":"unnamed-chunk-38","document_id":"91EA4602","expansion_state":0,"options":{},"row":240,"row_count":1,"visible":true},{"chunk_id":"chjlyqzast0wh","chunk_label":"unnamed-chunk-39","document_id":"91EA4602","expansion_state":0,"options":{},"row":244,"row_count":1,"visible":true},{"chunk_id":"cvccf6wng4jpt","chunk_label":"unnamed-chunk-40","document_id":"91EA4602","expansion_state":0,"options":{},"row":248,"row_count":1,"visible":true},{"chunk_id":"c5na68tbivrwp","chunk_label":"unnamed-chunk-41","document_id":"91EA4602","expansion_state":0,"options":{},"row":252,"row_count":1,"visible":true},{"chunk_id":"cwy29gz7w7v0c","chunk_label":"unnamed-chunk-42","document_id":"91EA4602","expansion_state":0,"options":{},"row":256,"row_count":1,"visible":true},{"chunk_id":"cynug6wzzct4t","chunk_label":"unnamed-chunk-43","document_id":"91EA4602","expansion_state":0,"options":{},"row":260,"row_count":1,"visible":true},{"chunk_id":"cd3ugnzhk3582","chunk_label":"unnamed-chunk-44","document_id":"91EA4602","expansion_state":0,"options":{},"row":265,"row_count":1,"visible":true},{"chunk_id":"ce6bqj22lc5o9","chunk_label":"unnamed-chunk-45","document_id":"91EA4602","expansion_state":0,"options":{},"row":270,"row_count":1,"visible":true},{"chunk_id":"cx0gk0k4k6nb6","chunk_label":"unnamed-chunk-46","document_id":"91EA4602","expansion_state":0,"options":{},"row":274,"row_count":1,"visible":true},{"chunk_id":"cujdh37icz50q","chunk_label":"unnamed-chunk-47","document_id":"91EA4602","expansion_state":0,"options":{},"row":281,"row_count":1,"visible":true},{"chunk_id":"cbjcah5yqhvzy","chunk_label":"unnamed-chunk-48","document_id":"91EA4602","expansion_state":0,"options":{},"row":285,"row_count":1,"visible":true},{"chunk_id":"civcefdm4ddyu","chunk_label":"unnamed-chunk-49","document_id":"91EA4602","expansion_state":0,"options":{},"row":289,"row_count":1,"visible":true},{"chunk_id":"cossycueiwi6m","chunk_label":"unnamed-chunk-50","document_id":"91EA4602","expansion_state":0,"options":{},"row":293,"row_count":1,"visible":true},{"chunk_id":"cc9emlfw4dh97","chunk_label":"unnamed-chunk-51","document_id":"91EA4602","expansion_state":0,"options":{},"row":297,"row_count":1,"visible":true},{"chunk_id":"c85ry1suesend","chunk_label":"unnamed-chunk-52","document_id":"91EA4602","expansion_state":0,"options":{},"row":302,"row_count":1,"visible":true},{"chunk_id":"carmhtcwlt453","chunk_label":"unnamed-chunk-53","document_id":"91EA4602","expansion_state":0,"options":{},"row":315,"row_count":1,"visible":true},{"chunk_id":"cyu7ddk6lkbne","chunk_label":"unnamed-chunk-54","document_id":"91EA4602","expansion_state":0,"options":{},"row":320,"row_count":1,"visible":true},{"chunk_id":"cfj2pl38lnj6g","chunk_label":"unnamed-chunk-55","document_id":"91EA4602","expansion_state":0,"options":{},"row":325,"row_count":1,"visible":true},{"chunk_id":"cn7sgxwggbfk4","chunk_label":"unnamed-chunk-56","document_id":"91EA4602","expansion_state":0,"options":{},"row":332,"row_count":1,"visible":true},{"chunk_id":"cry3ljqt0z97c","chunk_label":"unnamed-chunk-57","document_id":"91EA4602","expansion_state":0,"options":{},"row":338,"row_count":1,"visible":true},{"chunk_id":"cq0hwym5ftng0","chunk_label":"unnamed-chunk-58","document_id":"91EA4602","expansion_state":0,"options":{},"row":344,"row_count":1,"visible":true},{"chunk_id":"cxezgf98j5mmb","chunk_label":"unnamed-chunk-59","document_id":"91EA4602","expansion_state":0,"options":{},"row":350,"row_count":1,"visible":true},{"chunk_id":"cq94s01inmi17","chunk_label":"unnamed-chunk-60","document_id":"91EA4602","expansion_state":0,"options":{},"row":359,"row_count":1,"visible":true},{"chunk_id":"cqpo2fx4opvm0","chunk_label":"unnamed-chunk-61","document_id":"91EA4602","expansion_state":0,"options":{},"row":370,"row_count":1,"visible":true},{"chunk_id":"cqvpfkwzqii7y","chunk_label":"unnamed-chunk-62","document_id":"91EA4602","expansion_state":0,"options":{},"row":376,"row_count":1,"visible":true},{"chunk_id":"cxiuy41xm38kq","chunk_label":"unnamed-chunk-63","document_id":"91EA4602","expansion_state":0,"options":{},"row":383,"row_count":1,"visible":true},{"chunk_id":"cmm2ar1k7owvp","chunk_label":"unnamed-chunk-64","document_id":"91EA4602","expansion_state":0,"options":{},"row":387,"row_count":1,"visible":true},{"chunk_id":"c84rolgkbq1b6","chunk_label":"unnamed-chunk-65","document_id":"91EA4602","expansion_state":0,"options":{},"row":391,"row_count":1,"visible":true},{"chunk_id":"clyh0xyhnkb3j","chunk_label":"unnamed-chunk-66","document_id":"91EA4602","expansion_state":0,"options":{},"row":396,"row_count":1,"visible":true},{"chunk_id":"c3vd71qqm9a87","chunk_label":"unnamed-chunk-67","document_id":"91EA4602","expansion_state":0,"options":{},"row":401,"row_count":1,"visible":true},{"chunk_id":"cshxywpa6yeqt","chunk_label":"unnamed-chunk-68","document_id":"91EA4602","expansion_state":0,"options":{},"row":406,"row_count":1,"visible":true},{"chunk_id":"cn2icg8bsdufu","chunk_label":"unnamed-chunk-69","document_id":"91EA4602","expansion_state":0,"options":{},"row":418,"row_count":1,"visible":true},{"chunk_id":"ceyte8h2gs4is","chunk_label":"unnamed-chunk-70","document_id":"91EA4602","expansion_state":0,"options":{},"row":427,"row_count":1,"visible":true},{"chunk_id":"cycue2ow2i9sg","chunk_label":"unnamed-chunk-71","document_id":"91EA4602","expansion_state":0,"options":{},"row":435,"row_count":1,"visible":true},{"chunk_id":"csozum0zgbyb5","chunk_label":"unnamed-chunk-72","document_id":"91EA4602","expansion_state":0,"options":{},"row":444,"row_count":1,"visible":true},{"chunk_id":"cd0vud6qhmh4n","chunk_label":"unnamed-chunk-73","document_id":"91EA4602","expansion_state":0,"options":{},"row":463,"row_count":1,"visible":true},{"chunk_id":"cy64sdjzlfx8j","chunk_label":"unnamed-chunk-74","document_id":"91EA4602","expansion_state":0,"options":{},"row":471,"row_count":1,"visible":true},{"chunk_id":"coa3kdrxluh79","chunk_label":"unnamed-chunk-75","document_id":"91EA4602","expansion_state":0,"options":{},"row":477,"row_count":1,"visible":true},{"chunk_id":"cs70nei6y0xza","chunk_label":"unnamed-chunk-76","document_id":"91EA4602","expansion_state":0,"options":{},"row":482,"row_count":1,"visible":true},{"chunk_id":"clz3cfth3sgr5","chunk_label":"unnamed-chunk-77","document_id":"91EA4602","expansion_state":0,"options":{},"row":487,"row_count":1,"visible":true},{"chunk_id":"cpmirhdsu5eiq","chunk_label":"unnamed-chunk-78","document_id":"91EA4602","expansion_state":0,"options":{},"row":493,"row_count":1,"visible":true},{"chunk_id":"cm0xc37jai7xo","chunk_label":"unnamed-chunk-79","document_id":"91EA4602","expansion_state":0,"options":{},"row":500,"row_count":1,"visible":true},{"chunk_id":"ccmlcswitph9l","chunk_label":"unnamed-chunk-80","document_id":"91EA4602","expansion_state":0,"options":{},"row":505,"row_count":1,"visible":true},{"chunk_id":"cixy0kfwggrik","chunk_label":"unnamed-chunk-81","document_id":"91EA4602","expansion_state":0,"options":{},"row":511,"row_count":1,"visible":true},{"chunk_id":"c29wzrlucqmrn","chunk_label":"unnamed-chunk-82","document_id":"91EA4602","expansion_state":0,"options":{},"row":515,"row_count":1,"visible":true},{"chunk_id":"cvbgpm5da4nzo","chunk_label":"unnamed-chunk-83","document_id":"91EA4602","expansion_state":0,"options":{},"row":521,"row_count":1,"visible":true},{"chunk_id":"c6sm05ttgzhiy","chunk_label":"unnamed-chunk-84","document_id":"91EA4602","expansion_state":0,"options":{},"row":530,"row_count":1,"visible":true},{"chunk_id":"cacziyyd8npdp","chunk_label":"unnamed-chunk-85","document_id":"91EA4602","expansion_state":0,"options":{},"row":536,"row_count":1,"visible":true},{"chunk_id":"c7d87q2l7jv0y","chunk_label":"unnamed-chunk-86","document_id":"91EA4602","expansion_state":0,"options":{},"row":540,"row_count":1,"visible":true},{"chunk_id":"cw5krxjh5gcqt","chunk_label":"unnamed-chunk-87","document_id":"91EA4602","expansion_state":0,"options":{},"row":545,"row_count":1,"visible":true},{"chunk_id":"cnie2ksiemxlm","chunk_label":"unnamed-chunk-88","document_id":"91EA4602","expansion_state":0,"options":{},"row":550,"row_count":1,"visible":true},{"chunk_id":"c5xgzjtdabsq5","chunk_label":"unnamed-chunk-89","document_id":"91EA4602","expansion_state":0,"options":{},"row":554,"row_count":1,"visible":true},{"chunk_id":"cau9s62kreu7l","chunk_label":"unnamed-chunk-90","document_id":"91EA4602","expansion_state":0,"options":{},"row":558,"row_count":1,"visible":true},{"chunk_id":"cnm1w2534yias","chunk_label":"unnamed-chunk-91","document_id":"91EA4602","expansion_state":0,"options":{},"row":571,"row_count":1,"visible":true},{"chunk_id":"cmq9nlmz66alr","chunk_label":"unnamed-chunk-92","document_id":"91EA4602","expansion_state":0,"options":{},"row":583,"row_count":1,"visible":true},{"chunk_id":"c6xj36ihyg9jl","chunk_label":"unnamed-chunk-93","document_id":"91EA4602","expansion_state":0,"options":{},"row":588,"row_count":1,"visible":true},{"chunk_id":"cmcyj9e5lfa7j","chunk_label":"unnamed-chunk-94","document_id":"91EA4602","expansion_state":0,"options":{},"row":595,"row_count":1,"visible":true},{"chunk_id":"c6jn10b1wygce","chunk_label":"unnamed-chunk-95","document_id":"91EA4602","expansion_state":0,"options":{},"row":607,"row_count":1,"visible":true},{"chunk_id":"c0s89b1swv7ua","chunk_label":"unnamed-chunk-96","document_id":"91EA4602","expansion_state":0,"options":{},"row":612,"row_count":1,"visible":true},{"chunk_id":"cd57gbdmvamm6","chunk_label":"unnamed-chunk-97","document_id":"91EA4602","expansion_state":0,"options":{},"row":631,"row_count":1,"visible":true},{"chunk_id":"cicuoa35yt3nu","chunk_label":"unnamed-chunk-98","document_id":"91EA4602","expansion_state":0,"options":{},"row":643,"row_count":1,"visible":true},{"chunk_id":"c65f1vcli4vp7","chunk_label":"unnamed-chunk-99","document_id":"91EA4602","expansion_state":0,"options":{},"row":649,"row_count":1,"visible":true},{"chunk_id":"cr1mlnsxk1k6a","chunk_label":"unnamed-chunk-100","document_id":"91EA4602","expansion_state":0,"options":{},"row":660,"row_count":1,"visible":true},{"chunk_id":"cunjjzxxy78tp","chunk_label":"unnamed-chunk-101","document_id":"91EA4602","expansion_state":0,"options":{},"row":665,"row_count":1,"visible":true},{"chunk_id":"cgqbqnz7xc8qh","chunk_label":"unnamed-chunk-102","document_id":"91EA4602","expansion_state":0,"options":{},"row":673,"row_count":1,"visible":true},{"chunk_id":"chy4pwqness2h","chunk_label":"unnamed-chunk-103","document_id":"91EA4602","expansion_state":0,"options":{},"row":680,"row_count":1,"visible":true},{"chunk_id":"cvu0c8h2ukuir","chunk_label":"unnamed-chunk-104","document_id":"91EA4602","expansion_state":0,"options":{},"row":685,"row_count":1,"visible":true},{"chunk_id":"c79od2kb4nx1u","chunk_label":"unnamed-chunk-105","document_id":"91EA4602","expansion_state":0,"options":{},"row":690,"row_count":1,"visible":true},{"chunk_id":"cl3cl9analj8o","chunk_label":"unnamed-chunk-106","document_id":"91EA4602","expansion_state":0,"options":{},"row":696,"row_count":1,"visible":true},{"chunk_id":"c6ccentj3znlv","chunk_label":"unnamed-chunk-107","document_id":"91EA4602","expansion_state":0,"options":{},"row":702,"row_count":1,"visible":true},{"chunk_id":"cnu3lxdz7mxoq","chunk_label":"unnamed-chunk-108","document_id":"91EA4602","expansion_state":0,"options":{},"row":709,"row_count":1,"visible":true}],"chunk_rendered_width":700,"default_chunk_options":{"echo":true},"doc_write_time":1590455109,"working_dir":null}